README.txt
setup.py
ZenQueue.egg-info/PKG-INFO
ZenQueue.egg-info/SOURCES.txt
ZenQueue.egg-info/dependency_links.txt
ZenQueue.egg-info/requires.txt
ZenQueue.egg-info/top_level.txt
zenqueue/__init__.py
zenqueue/log.py
zenqueue/client/__init__.py
zenqueue/client/benchmark.py
zenqueue/client/common.py
zenqueue/client/http/__init__.py
zenqueue/client/http/async.py
zenqueue/client/http/common.py
zenqueue/client/http/sync.py
zenqueue/client/native/__init__.py
zenqueue/client/native/async.py
zenqueue/client/native/common.py
zenqueue/client/native/sync.py
zenqueue/queue/__init__.py
zenqueue/queue/async.py
zenqueue/queue/common.py
zenqueue/queue/sync.py
zenqueue/server/__init__.py
zenqueue/server/http.py
zenqueue/server/native.py
zenqueue/utils/__init__.py
zenqueue/utils/async.py
zenqueue/utils/sync.py