Metadata-Version: 1.0
Name: ZenQueue
Version: 0.5.2
Summary: An incredibly simple (but fast) network message queueing system, written in Python.
Home-page: http://github.com/disturbyte/zenqueue
Author: Zachary Voase
Author-email: disturbyte@gmail.com
License: UNKNOWN
Platform: UNKNOWN
